PageObjectLibrary/__init__.py
PageObjectLibrary/keywords.py
PageObjectLibrary/locatormap.py
PageObjectLibrary/pageobject.py
PageObjectLibrary/version.py
robotframework_pageobjectlibrary-1.1.dist-info/LICENSE
robotframework_pageobjectlibrary-1.1.dist-info/METADATA
robotframework_pageobjectlibrary-1.1.dist-info/WHEEL
robotframework_pageobjectlibrary-1.1.dist-info/top_level.txt
robotframework_pageobjectlibrary-1.1.dist-info/zip-safe
robotframework_pageobjectlibrary-1.1.dist-info/RECORD
