Metadata-Version: 2.1
Name: robotframework-pageobjectlibrary
Version: 1.1
Summary: RobotFramework library that implements the Page Object pattern
Home-page: https://github.com/boakley/robotframework-pageobjectlibrary/
Author: Bryan Oakley
Author-email: bryan.oakley@gmail.com
License: Apache License 2.0
Keywords: robotframework
Platform: UNKNOWN
Classifier: Development Status :: 5 - Production/Stable
Classifier: License :: OSI Approved :: Apache Software License
Classifier: Operating System :: OS Independent
Classifier: Framework :: Robot Framework
Classifier: Programming Language :: Python
Classifier: Topic :: Software Development :: Testing
Classifier: Topic :: Software Development :: Quality Assurance
Classifier: Intended Audience :: Developers
License-File: LICENSE
Requires-Dist: robotframework
Requires-Dist: robotframework-seleniumlibrary
Requires-Dist: selenium
Requires-Dist: six
